browser_mcp/__init__.py
browser_mcp/__main__.py
browser_mcp/check_playwright.py
browser_mcp/server.py
browser_mcp/test.py
browser_mcp-0.1.5.dist-info/LICENSE
browser_mcp-0.1.5.dist-info/METADATA
browser_mcp-0.1.5.dist-info/WHEEL
browser_mcp-0.1.5.dist-info/entry_points.txt
browser_mcp-0.1.5.dist-info/top_level.txt
browser_mcp-0.1.5.dist-info/RECORD
