Metadata-Version: 2.2
Name: browser-mcp
Version: 0.1.5
Summary: MCP server for browser-use
Project-URL: Homepage, https://github.com/pranav7/browser-mcp
Project-URL: Bug Tracker, https://github.com/pranav7/browser-mcp/issues
Requires-Python: >=3.13
License-File: LICENSE
Requires-Dist: mcp[cli]>=1.3.0
Requires-Dist: browser-use>=0.1.4
Requires-Dist: ruff>=0.9.10
Requires-Dist: langchain-openai>=0.3.1
Requires-Dist: python-dotenv>=1.0.1
Requires-Dist: playwright>=1.50.0
Requires-Dist: uv>=0.1.0
Requires-Dist: pytest>=7.4.0
